[
  {
    "地质水文条件": "区域地质及构造分布",
    "区域地质及构造分布": "1",
    "地层岩性": "5",
    "构造特征": "4",
    "水文地质条件": "2",
    "ωᵢᵥ": "2.5149",
    "ωⁱᵥ": "0.5323",
    "Δωⁱᵥ": "2.2184",
    "λmax": "4.1674"
  },
  {
    "地质水文条件": "地层岩性",
    "区域地质及构造分布": "1/5",
    "地层岩性": "1",
    "构造特征": "2",
    "水文地质条件": "1",
    "ωᵢᵥ": "0.7953",
    "ωⁱᵥ": "0.1675",
    "Δωⁱᵥ": "0.6982",
    "λmax": "4.1674"
  },
  {
    "地质水文条件": "构造特征",
    "区域地质及构造分布": "1/4",
    "地层岩性": "1/2",
    "构造特征": "1",
    "水文地质条件": "1",
    "ωᵢᵥ": "0.5946",
    "ωⁱᵥ": "0.1241",
    "Δωⁱᵥ": "0.5170",
    "λmax": "4.1674"
  },
  {
    "地质水文条件": "水文地质条件",
    "区域地质及构造分布": "1/2",
    "地层岩性": "1",
    "构造特征": "1",
    "水文地质条件": "1",
    "ωᵢᵥ": "0.8409",
    "ωⁱᵥ": "0.1761",
    "Δωⁱᵥ": "0.7338",
    "λmax": "4.1674"
  }
]